{
  "slug": "半导体泡沫-双重警示",
  "keywords": [
    "SOX指数",
    "半导体泡沫",
    "迈克尔·伯里",
    "SOXX看跌期权",
    "RSI超买",
    "杰文斯悖论",
    "周期末段紧缩",
    "高盛Delta One",
    "英伟达",
    "AI算力"
  ],
  "meta": {
    "issue_no": "",
    "date": "2026.04.25",
    "topic_tag": "市场情绪 · SEMIS × VALUATION",
    "rating": "★★ 必读 · MUST READ",
    "kicker_default": "DAILY BRIEF · 今日信号",
    "focus_name": "顶级机构研报精选"
  },
  "cover": {
    "title": "SOX 创新高那一天<br>{em}泡沫警报{/em}也<br>同步亮起",
    "dek": "费城半导体指数 18 连涨、RSI 突破 85，迈克尔·伯里买入 SOXX 看跌期权——多空分歧创近年最大；同一天，《华尔街日报》指出这是 1985 年以来罕见的「股价新高 + 市盈率反而下跌」。",
    "source_name": "SupSub · 关注点",
    "source_meta": "本期信号来自 <strong>SupSub · 顶级机构研报精选</strong> 关注点的交叉聚合",
    "kpi": [
      {
        "key": "SOX 连涨",
        "value": "18 天",
        "tone": "up"
      },
      {
        "key": "SOXX 高估",
        "value": "+65.4%",
        "tone": "up"
      },
      {
        "key": "SOXX PE",
        "value": "39.85×"
      }
    ]
  },
  "abstract": {
    "title": "SOX 创新高的同时，泡沫预警也来到峰值",
    "byline": "多源同日信号交叉佐证 · 2026.04.25",
    "abstract": "今日同一窗口出现 4 条相互呼应的信号：<ul><li>费城半导体指数 SOX 录得 <strong>18 个交易日</strong>连续上涨，相对 200 日均线偏离度达历史极值，RSI 突破 <strong>85</strong>，期权隐含波动率结构失衡；</li><li>「大空头」迈克尔·伯里买入 iShares 半导体 ETF（<strong>SOXX</strong>）看跌期权建立空头头寸；SOXX 当前 461.60 美元较其内在价值 279.00 美元高估 <strong>65.4%</strong>，市盈率 <strong>39.85 倍</strong>；</li><li>高盛 Delta One 交易台 Rich Privorotsky 提出「周期末段紧缩」判断——AI 推动的算力/电力/基建需求正在加速消耗资源；</li><li>反向论据来自《华尔街日报》：1985 年以来罕见的「股价创新高 + 市盈率反而下跌」，AI 算力需求 + 伊朗战争推高企业盈利做大了分母。</li></ul>",
    "editor_note": "这不是一条孤立的「估值偏高」提醒，是 {em}多空双方第一次把账面摊开{/em}。落到两类读者：<ol><li>对 A/H 股投资人 —— 半导体高位降低单一龙头权重，盯紧 MAG7 龙头股是否补涨、英伟达滞后能否修复；</li><li>对周期投资者 —— 关注 SOX 与 200 日均线偏离度何时收敛、隐含波动率结构是否反转，这两个指标比绝对点位更早。</li></ol>"
  },
  "takeaways": {
    "title": "一天之内，{em}多空两边{/em}的硬数字同时摆上桌",
    "items": [
      {
        "title": "技术面极端：SOX 18 连涨破纪录",
        "body": "费城半导体指数连续 <strong>18 天</strong>上涨突破历史高位，相对 200 日均线偏离度达历史极值，<strong>RSI 突破 85</strong>，期权隐含波动率结构失衡——四个超买信号同时亮灯。"
      },
      {
        "title": "大佬空头：伯里 SOXX 看跌期权",
        "body": "迈克尔·伯里买入 SOXX 看跌期权建立空头头寸；SOXX <strong>461.60 美元</strong>较内在价值 279.00 美元高估 <strong>65.4%</strong>，市盈率 <strong>39.85 倍</strong>，远超历史水平。"
      },
      {
        "title": "资金面失衡：龙头股反而盘整",
        "body": "MAG7 等龙头股近期陷入盘整、英伟达等核心标的表现滞后——上涨更像是流动性追涨投机，而非基本面共振；高盛交易台称之为<strong>「周期末段紧缩」</strong>。"
      },
      {
        "title": "反向论据：WSJ 的杰文斯悖论",
        "body": "《华尔街日报》指出这是 <strong>1985 年</strong>以来罕见的「高股价 + 低 PE」组合，AI 算力 + 战争盈利做大了分母；按杰文斯悖论，算力效率提升不会导致需求崩塌——多空分歧由此创近年最大。"
      }
    ]
  },
  "quote": {
    "text": "市场已经进入<br>{em}周期末段的紧缩{/em}阶段。",
    "cite": "Rich Privorotsky · 高盛 Delta One 交易台负责人",
    "context": "—— 这不是普通的高位震荡。AI 需求把资源消耗推进了周期最后一档，超买指标和资金面的背离同步出现。"
  },
  "further": {
    "title": "把今天的信号连成一张地图",
    "groups": [
      {
        "title": "技术面警钟",
        "items": [
          {
            "text": "SOX 指数 18 个交易日连涨创新高"
          },
          {
            "text": "RSI 破 85 + 期权隐含波动率结构失衡"
          }
        ]
      },
      {
        "title": "估值锚点 · 大佬出手",
        "items": [
          {
            "text": "伯里买入 SOXX 看跌期权建立空头"
          },
          {
            "text": "SOXX PE 39.85 倍 · 较内在价值高估 65.4%"
          }
        ]
      },
      {
        "title": "反向论据 · 多空分歧",
        "items": [
          {
            "text": "WSJ：1985 年来罕见的「新高 + 低 PE」"
          },
          {
            "text": "杰文斯悖论支持算力长期需求"
          }
        ]
      },
      {
        "title": "资金面落点",
        "items": [
          {
            "text": "MAG7 龙头股盘整 · 英伟达表现滞后"
          },
          {
            "text": "高盛 Delta One：周期末段紧缩"
          },
          {
            "text": "英伟达市值已破 5 万亿 → 边际推力衰减"
          }
        ]
      }
    ]
  }
}
